inspire_info/Author.py
inspire_info/InspireInfo.py
inspire_info/LatexCreator.py
inspire_info/Publication.py
inspire_info/__init__.py
inspire_info/myutils.py
inspire_info/scripts/__init__.py
inspire_info/scripts/create_cache_file.py
inspire_info/scripts/create_latex_doc.py
inspire_info/scripts/create_publication_history.py
inspire_info/scripts/get_papers.py
inspire_info/scripts/loop_over_author_files.py
inspire_info/scripts/merge_bibtex_files.py
inspire_info/scripts/search_authors_and_download.py
inspire_info/scripts/search_publication_by_title.py
inspire_info-0.1.15.dist-info/AUTHORS.rst
inspire_info-0.1.15.dist-info/LICENSE
inspire_info-0.1.15.dist-info/METADATA
inspire_info-0.1.15.dist-info/WHEEL
inspire_info-0.1.15.dist-info/entry_points.txt
inspire_info-0.1.15.dist-info/top_level.txt
inspire_info-0.1.15.dist-info/RECORD
