Metadata-Version: 2.1
Name: inspire-info
Version: 0.1.15
Summary: Package to retrieve more complex info from inspire than the web-interface allows
Home-page: https://github.com/WolfXeHD/inspire_info
Author: Tim Wolf
Author-email: tim.wolf@mpi-hd.mpg.de
License: MIT license
Keywords: inspire_info
Platform: UNKNOWN
Classifier: Development Status :: 2 - Pre-Alpha
Classifier: Intended Audience :: Developers
Classifier: License :: OSI Approved :: MIT License
Classifier: Natural Language :: English
Classifier: Programming Language :: Python :: 3.7
Classifier: Programming Language :: Python :: 3.8
Classifier: Programming Language :: Python :: 3.9
Requires-Python: >=3.7
Requires-Dist: beautifulsoup4 (>=4.11.1)
Requires-Dist: numpy (>=1.19.4)
Requires-Dist: pandas (>=1.2)
Requires-Dist: pandas-stubs (>=1.2.0.49)
Requires-Dist: PyYAML (>=6.0)
Requires-Dist: requests (>=2.25.1)
Requires-Dist: setuptools (>=65.4.1)
Requires-Dist: tqdm (==4.61.0)
